LICENSE
MANIFEST.in
README.md
setup.cfg
setup.py
india/__init__.py
india/cities.py
india/config.py
india/pincodes.py
india/states.py
india/towns.py
india/utils.py
india/data/cities.csv
india/data/pincodes.csv
india/data/states.csv
india/data/towns.csv
india/data/ut.csv
indian_states.egg-info/PKG-INFO
indian_states.egg-info/SOURCES.txt
indian_states.egg-info/dependency_links.txt
indian_states.egg-info/not-zip-safe
indian_states.egg-info/top_level.txt