Metadata-Version: 2.1
Name: indian-states
Version: 1.0
Summary: India's states and cities
Home-page: https://github.com/ArunKumar006/indian-states
Author: Rishabh Batra
Author-email: arunyuvi0206@gmail.com
License: UNKNOWN
Platform: UNKNOWN
Classifier: Programming Language :: Python :: 3.7
Classifier: License :: OSI Approved :: MIT License
Classifier: Operating System :: OS Independent
